schore/__init__.py
schore/py.typed
schore/type_aliases.py
schore/type_defs.py
schore/data/__init__.py
schore/data/df_manager.py
schore/data/table_2d_manager.py
schore/parameters/__init__.py
schore/parameters/processing_time/__init__.py
schore/parameters/processing_time/job_mc_p.py
schore/parameters/processing_time/job_stage_p.py
schore/parameters_examples/__init__.py
schore/parameters_examples/parallel_shop/__init__.py
schore/parameters_examples/parallel_shop/identical_flow/__init__.py
schore/parameters_examples/parallel_shop/identical_flow/hybrid_flowshop.py
schore/schedule/__init__.py
schore/schedule/abstract/__init__.py
schore/schedule/abstract/activity.py
schore/schedule/abstract/parallel_resource_group.py
schore/schedule/abstract/resource.py
schore/schedule/abstract/resource_group.py
schore/schedule_examples/__init__.py
schore/schedule_examples/machine.py
schore/schedule_examples/parallel_shop/__init__.py
schore/schedule_examples/parallel_shop/identical_flow/__init__.py
schore/schedule_examples/parallel_shop/identical_flow/hybrid_flowshop_machine.py
schore/schedule_examples/parallel_shop/identical_flow/hybrid_flowshop_operation.py
schore/schedule_examples/parallel_shop/identical_flow/hybrid_flowshop_schedule.py
schore/schedule_examples/parallel_shop/identical_flow/hybrid_flowshop_stage.py
schore/util/__init__.py
schore/util/text_data_parser.py
schore-0.0.4.dist-info/METADATA
schore-0.0.4.dist-info/WHEEL
schore-0.0.4.dist-info/licenses/LICENSE
schore-0.0.4.dist-info/RECORD
