Metadata-Version: 2.4
Name: schore
Version: 0.0.4
Summary: Core classes for scheduling problems' definition
Project-URL: Repository, https://github.com/MSOLab/schore.git
Author-email: JuneTech <junetech0@gmail.com>
License-Expression: MIT
License-File: LICENSE
Requires-Python: >=3.11
Requires-Dist: pandas>=2.2.3
